{
  "session_id": "0ea677cb-31db-496d-b3eb-81e0e6b1cfe7",
  "state": "awaiting_answers",
  "created_at": "2026-01-21T09:58:11.509428",
  "updated_at": "2026-01-21T09:58:29.274035",
  "goal": "Automate code reviews for Python projects",
  "goal_analysis": {
    "intent": "Automated code review",
    "domain": "code_review",
    "confidence": 0.8,
    "ambiguities": [
      "Review focus areas not specified"
    ],
    "assumptions": [
      "Assuming code is version-controlled (git)",
      "Assuming PR/diff-based review workflow"
    ]
  },
  "requirements": {
    "must_have": [],
    "should_have": [],
    "must_not_have": [],
    "technical_constraints": {},
    "quality_attributes": {}
  },
  "question_rounds": [],
  "current_round": 0,
  "error": null,
  "metadata": {}
}
