{
  "session_id": "28c1d23f-f39f-4c6e-b996-646173738ad9",
  "state": "awaiting_answers",
  "created_at": "2026-01-21T23:53:52.287899",
  "updated_at": "2026-01-21T23:54:06.712588",
  "goal": "Automate code reviews",
  "goal_analysis": {
    "intent": "Automated code review",
    "domain": "code_review",
    "confidence": 0.6,
    "ambiguities": [
      "Programming language not specified",
      "Review focus areas not specified"
    ],
    "assumptions": [
      "Assuming code is version-controlled (git)",
      "Assuming PR/diff-based review workflow"
    ]
  },
  "requirements": {
    "must_have": [],
    "should_have": [],
    "must_not_have": [],
    "technical_constraints": {},
    "quality_attributes": {}
  },
  "question_rounds": [],
  "current_round": 0,
  "error": null,
  "metadata": {}
}