{
  "session_id": "b1ec94ca-ec68-4799-9b5e-de5fc28912cf",
  "state": "awaiting_answers",
  "created_at": "2026-01-22T09:53:13.758392",
  "updated_at": "2026-01-22T09:53:28.250511",
  "goal": "Automate code reviews",
  "goal_analysis": {
    "intent": "Automated code review",
    "domain": "code_review",
    "confidence": 0.6,
    "ambiguities": [
      "Programming language not specified",
      "Review focus areas not specified"
    ],
    "assumptions": [
      "Assuming code is version-controlled (git)",
      "Assuming PR/diff-based review workflow"
    ]
  },
  "requirements": {
    "must_have": [],
    "should_have": [],
    "must_not_have": [],
    "technical_constraints": {},
    "quality_attributes": {}
  },
  "question_rounds": [],
  "current_round": 0,
  "error": null,
  "metadata": {}
}
